[1,["ecpdLyjvZBwrvm+cedCcQy","169f8dd00","18872a2aa","1c7cdda52","16a52e6a3","7fmyH1dXZPxa5GFXsdmX+0","bb/M3Jw1ZL3ZrmcEHp8DB5","0dawqj1dxIp4gddNHBAtZL","22Aaa7OIRE5ZnrMqrIl35u","f2WT/1J81Pia5BPlUMvh9C","7fsR3QQmxHEqq6VJxPEqvT","f2W+5c4m1K+78FF3RP0lGc","6dDX0JDuZAybNyB8Vqo0A3","a2MjXRFdtLlYQ5ouAFv/+R","12882af9b","1f8f6f14c"],["node","_spriteFrame","_textureSetter","root","data"],["cc.SpriteFrame",["cc.Node",["_name","_opacity","_groupIndex","_active","_components","_prefab","_contentSize","_parent","_trs","_children"],-1,9,4,5,1,7,2],["cc.PrefabInfo",["fileId","root","asset"],2,1,1],["cc.Sprite",["_sizeMode","node","_materials","_spriteFrame"],2,1,3,6],["cc.PolygonCollider",["node","points","_offset"],3,1,12,5],["cc.Prefab",["_name"],2],["3cd09i0zeVAB7YmIGwCs4wQ",["node"],3,1],["ded8b+z3TpK7LhycJcsowKx",["node"],3,1],["cc.BlockInputEvents",["node"],3,1]],[[2,0,1,2,2],[3,1,2,3,1],[1,0,7,4,5,6,8,2],[1,0,2,7,4,5,6,8,3],[1,0,1,7,4,5,6,8,3],[5,0,2],[1,0,9,4,5,6,2],[1,0,3,1,7,4,5,6,4],[1,0,7,4,5,6,2],[6,0,1],[2,1,2,1],[3,0,1,2,3,2],[4,0,1,1],[4,0,2,1,1],[7,0,1],[8,0,1]],[[[{"name":"img_33","rect":[490,681,215,336],"offset":[0,0],"originalSize":[215,336],"capInsets":[0,0,0,0]}],[0],0,[0],[2],[3]],[[{"name":"img_35","rect":[202,846,173,352],"offset":[0,0],"originalSize":[173,352],"rotated":1,"capInsets":[0,0,0,0]}],[0],0,[0],[2],[1]],[[{"name":"img_38","rect":[734,955,122,66],"offset":[0,0],"originalSize":[122,66],"capInsets":[0,0,0,0]}],[0],0,[0],[2],[2]],[[{"name":"img_timu_7","rect":[737,741,200,44],"offset":[0,0],"originalSize":[200,44],"rotated":1,"capInsets":[0,0,0,0]}],[0],0,[0],[2],[4]],[[{"name":"img_34","rect":[457,736,271,275],"offset":[0,0],"originalSize":[271,275],"capInsets":[0,0,0,0]}],[0],0,[0],[2],[2]],[[[5,"Lv_7"],[6,"Lv_7",[-3,-4,-5,-6,-7,-8,-9,-10,-11],[[9,-2]],[10,-1,0],[5,750,1334]],[3,"img_38",1,1,[[1,-12,[14],15],[12,-13,[[[0,-57.4,-26],[0,-31.5,-31.3],[0,-16.7,-17.6],[0,-3.4,-31.1],[0,13.6,-19.6],[0,8.6,-9.5],[0,40.2,7.8],[0,59.6,14.4],[0,56.9,27.2],[0,39.1,26.2],[0,38.8,32.1],[0,-60.6,14.7],[0,-52.3,-6.8]],8,8,8,8,8,8,8,8,8,8,8,8,8]],[14,-14]],[0,"f8LouYJSFNPKGXoxtxI5eF",1,0],[5,122,66],[39.232,147.237,0,0,0,0,1,1,1,1]],[3,"img_35",2,1,[[1,-15,[6],7],[13,-16,[0,53.6,29.1],[[[0,-9.6,-18.9],[0,15.6,-5.7],[0,28.8,33.5],[0,-91,143.9],[0,-120,-48]],8,8,8,8,8]]],[0,"9bv6aFl1pOoY738eQvXeCv",1,0],[5,173,352],[-200.728,-50.86,0,0,0,0,1,1,1,1]],[7,"mask",false,0,1,[[11,0,-17,[16],17],[15,-18]],[0,"dcibK+j11NW7KuSCg2GP5q",1,0],[5,750,600]],[2,"img_timu_7",1,[[1,-19,[0],1]],[0,"f3rAFvexpGbKX9Gbicxpst",1,0],[5,200,44],[0,470,0,0,0,0,1,1,1,1]],[8,"img_39",1,[[1,-20,[2],3]],[0,"b73abwSHBLfY44oHey8R90",1,0],[5,750,715]],[2,"img_33",1,[[1,-21,[4],5]],[0,"cdLpPulBJCc6srH6esLLqc",1,0],[5,215,336],[238.321,-63.074,0,0,0,0,1,1,1,1]],[4,"img_36",0,1,[[1,-22,[8],9]],[0,"25mHb/kV1PybUVigmF/ime",1,0],[5,173,352],[-201.012,-51.192,0,0,0,0,1,1,1,1]],[4,"img_34",0,1,[[1,-23,[10],11]],[0,"59ChKqoDJOgrRhxBsveuuQ",1,0],[5,271,275],[272.816,-71.794,0,0,0,0,1,1,1,1]],[2,"img_37",1,[[1,-24,[12],13]],[0,"09xp/BMnVGWo1OC+7KqQAv",1,0],[5,162,195],[27.6,148.729,0,0,0,0,1,1,1,1]]],0,[0,3,1,0,0,1,0,-1,5,0,-2,6,0,-3,7,0,-4,3,0,-5,8,0,-6,9,0,-7,10,0,-8,2,0,-9,4,0,0,2,0,0,2,0,0,2,0,0,3,0,0,3,0,0,4,0,0,4,0,0,5,0,0,6,0,0,7,0,0,8,0,0,9,0,0,10,0,4,1,24],[0,0,0,0,0,0,0,0,0,0,0,0,0,0,0,0,0,0],[-1,1,-1,1,-1,1,-1,1,-1,1,-1,1,-1,1,-1,1,-1,1],[0,5,0,6,0,7,0,8,0,9,0,10,0,11,0,12,0,13]],[[{"name":"img_39","rect":[3,3,750,715],"offset":[0,0],"originalSize":[750,715],"capInsets":[0,0,0,0]}],[0],0,[0],[2],[14]],[[{"name":"img_36","rect":[560,846,173,352],"offset":[0,0],"originalSize":[173,352],"rotated":1,"capInsets":[0,0,0,0]}],[0],0,[0],[2],[1]],[[{"name":"img_37","rect":[683,854,162,195],"offset":[0,0],"originalSize":[162,195],"rotated":1,"capInsets":[0,0,0,0]}],[0],0,[0],[2],[15]]]]