{"length":71709,"bmp":109890,"beatDuration":545,"keyValues":[{"key":"speed","value":"22"},{"key":"difficulty","value":"1"}],"notes":[{"time":0,"x":0},{"time":789,"x":0},{"time":1950,"x":0},{"time":3014,"x":18000},{"time":3483,"x":0},{"time":4063,"x":18000},{"time":4644,"x":-13000},{"time":5224,"x":0},{"time":5750,"x":-13000},{"time":6269,"x":0},{"time":6757,"x":19000},{"time":7338,"x":19000},{"time":7872,"x":42000},{"time":8382,"x":42000},{"time":8963,"x":30000},{"time":9520,"x":0},{"time":10054,"x":-12000},{"time":10622,"x":-12000},{"time":11122,"x":-24000},{"time":11726,"x":-35000},{"time":12190,"x":-24000},{"time":12794,"x":0},{"time":13351,"x":18000},{"time":13839,"x":0},{"time":14396,"x":-14000},{"time":15000,"x":0},{"time":15511,"x":-15000},{"time":16022,"x":-15000},{"time":16579,"x":0},{"time":17136,"x":12000},{"time":17717,"x":12000},{"time":18228,"x":12000},{"time":18413,"x":12000},{"time":18596,"x":12000},{"time":19598,"x":0},{"time":19853,"x":0},{"time":20132,"x":0},{"time":20410,"x":0},{"time":20968,"x":-16000},{"time":21502,"x":0},{"time":22059,"x":20000},{"time":22570,"x":0},{"time":23150,"x":0},{"time":23661,"x":-10000},{"time":24242,"x":-10000},{"time":24776,"x":-10000},{"time":25333,"x":0},{"time":25844,"x":0},{"time":26424,"x":0},{"time":26958,"x":-11000},{"time":27237,"x":-11000},{"time":27516,"x":-11000},{"time":27794,"x":-11000},{"time":28050,"x":-11000},{"time":28305,"x":-11000},{"time":28607,"x":-29000},{"time":28862,"x":-29000},{"time":29141,"x":-29000},{"time":29698,"x":0},{"time":30209,"x":14000},{"time":30790,"x":0},{"time":31324,"x":15000},{"time":31881,"x":0},{"time":32392,"x":-15000},{"time":32972,"x":-15000},{"time":33506,"x":-15000},{"time":34040,"x":0},{"time":34575,"x":10000},{"time":34853,"x":10000},{"time":35155,"x":10000},{"time":35459,"x":10000},{"time":36827,"x":0},{"time":37918,"x":0},{"time":38406,"x":-12000},{"time":39010,"x":0},{"time":39520,"x":12000},{"time":40092,"x":0},{"time":40650,"x":-13000},{"time":41185,"x":0},{"time":41694,"x":-13000},{"time":42191,"x":-13000},{"time":42748,"x":-13000},{"time":43305,"x":0},{"time":43862,"x":0},{"time":44412,"x":0},{"time":44931,"x":15000},{"time":45513,"x":15000},{"time":46022,"x":0},{"time":46626,"x":0},{"time":47113,"x":-15000},{"time":47671,"x":-23000},{"time":48274,"x":-23000},{"time":48808,"x":0},{"time":49296,"x":0},{"time":49871,"x":14000},{"time":50434,"x":0},{"time":51002,"x":0},{"time":51524,"x":-10000},{"time":52059,"x":0},{"time":52623,"x":0},{"time":53127,"x":0},{"time":53685,"x":14000},{"time":54846,"x":0},{"time":55333,"x":-13000},{"time":55844,"x":0},{"time":56424,"x":-13000},{"time":56982,"x":0},{"time":57560,"x":9000},{"time":58584,"x":0},{"time":59164,"x":-11000},{"time":59698,"x":0},{"time":60511,"x":11000},{"time":60790,"x":11000},{"time":61045,"x":11000},{"time":61324,"x":11000},{"time":61904,"x":0},{"time":62146,"x":0},{"time":62415,"x":0},{"time":62671,"x":0},{"time":63530,"x":-14000},{"time":64087,"x":0},{"time":64621,"x":-14000},{"time":65155,"x":0},{"time":65666,"x":-14000},{"time":66247,"x":0},{"time":66781,"x":0},{"time":67338,"x":0},{"time":67872,"x":12000},{"time":68429,"x":12000},{"time":68963,"x":0},{"time":69497,"x":0},{"time":70055,"x":-16000},{"time":70612,"x":-16000},{"time":71146,"x":-16000}]}