{"length":52844,"bmp":118035,"beatDuration":506,"keyValues":[{"key":"speed","value":"22"},{"key":"difficulty","value":"1"}],"notes":[{"time":0,"x":0,"l":1},{"time":534,"x":0,"l":1},{"time":998,"x":0,"l":1},{"time":1277,"x":0,"l":0},{"time":1509,"x":0,"l":0},{"time":1672,"x":0,"l":0},{"time":2043,"x":0,"l":0},{"time":2531,"x":0,"l":0},{"time":3065,"x":0,"l":0},{"time":3553,"x":0,"l":0},{"time":3808,"x":0,"l":0},{"time":4087,"x":0,"l":1},{"time":4598,"x":45000,"l":0},{"time":5085,"x":45000,"l":0},{"time":5596,"x":45000,"l":0},{"time":6107,"x":45000,"l":0},{"time":6618,"x":45000,"l":0},{"time":7129,"x":42000,"l":0},{"time":7639,"x":42000,"l":0},{"time":8150,"x":0,"l":1},{"time":8638,"x":0,"l":0},{"time":9149,"x":0,"l":0},{"time":9683,"x":0,"l":0},{"time":10170,"x":0,"l":0},{"time":10681,"x":0,"l":0},{"time":11192,"x":0,"l":0},{"time":11703,"x":0,"l":0},{"time":12214,"x":0,"l":1},{"time":12725,"x":-48000,"l":0},{"time":13235,"x":-48000,"l":0},{"time":13746,"x":-48000,"l":0},{"time":14257,"x":-48000,"l":0},{"time":14745,"x":-25000,"l":0},{"time":15271,"x":-25000,"l":0},{"time":15766,"x":-25000,"l":0},{"time":16277,"x":-25000,"l":1},{"time":16788,"x":0,"l":0},{"time":17299,"x":0,"l":0},{"time":17810,"x":0,"l":0},{"time":18297,"x":0,"l":0},{"time":18831,"x":0,"l":0},{"time":20364,"x":0,"l":1},{"time":20852,"x":0,"l":0},{"time":21362,"x":0,"l":0},{"time":21850,"x":0,"l":0},{"time":22384,"x":0,"l":0},{"time":22895,"x":0,"l":0},{"time":23382,"x":0,"l":0},{"time":23893,"x":0,"l":0},{"time":24404,"x":0,"l":0},{"time":24915,"x":0,"l":1},{"time":25426,"x":-38000,"l":0},{"time":25937,"x":-38000,"l":0},{"time":26448,"x":-38000,"l":0},{"time":26958,"x":-38000,"l":0},{"time":27446,"x":-38000,"l":0},{"time":27957,"x":-26000,"l":0},{"time":28468,"x":-26000,"l":0},{"time":28979,"x":0,"l":1},{"time":29489,"x":44000,"l":0},{"time":30000,"x":44000,"l":0},{"time":30511,"x":44000,"l":0},{"time":31022,"x":44000,"l":0},{"time":31533,"x":44000,"l":0},{"time":32044,"x":44000,"l":0},{"time":32531,"x":44000,"l":0},{"time":33065,"x":0,"l":1},{"time":33553,"x":0,"l":0},{"time":34064,"x":0,"l":0},{"time":34342,"x":0,"l":0},{"time":34575,"x":0,"l":0},{"time":34830,"x":0,"l":0},{"time":35085,"x":0,"l":0},{"time":35596,"x":0,"l":0},{"time":35852,"x":0,"l":0},{"time":36084,"x":0,"l":0},{"time":36618,"x":0,"l":1},{"time":37105,"x":-41000,"l":0},{"time":37616,"x":-41000,"l":0},{"time":37872,"x":-41000,"l":0},{"time":38143,"x":-41000,"l":0},{"time":38661,"x":-41000,"l":0},{"time":39172,"x":0,"l":1},{"time":39683,"x":0,"l":0},{"time":39938,"x":0,"l":0},{"time":40310,"x":0,"l":0},{"time":40705,"x":0,"l":0},{"time":41215,"x":0,"l":0},{"time":41703,"x":0,"l":0},{"time":42034,"x":0,"l":0},{"time":42353,"x":0,"l":0},{"time":42701,"x":0,"l":0},{"time":43212,"x":0,"l":1},{"time":43723,"x":41000,"l":0},{"time":44002,"x":41000,"l":0},{"time":44281,"x":41000,"l":0},{"time":44745,"x":41000,"l":0},{"time":46788,"x":0,"l":0},{"time":48808,"x":-46000,"l":0},{"time":49064,"x":-46000,"l":0},{"time":49319,"x":-46000,"l":0},{"time":49575,"x":-46000,"l":0},{"time":49830,"x":-46000,"l":0},{"time":50085,"x":-46000,"l":0},{"time":50341,"x":-46000,"l":0},{"time":50852,"x":0,"l":1},{"time":51339,"x":0,"l":0},{"time":51595,"x":0,"l":0},{"time":51873,"x":0,"l":0},{"time":52129,"x":0,"l":0},{"time":52384,"x":0,"l":0},{"time":52616,"x":0,"l":0}]}