[1,["71dzV2h4FLp76qHcel0VWd@6c48a"],0,[["sp.SkeletonData",["_name","_atlasText","textureNames","_skeletonJson","textures"],-1,3]],[[0,0,1,2,3,4,5]],[[0,"skel_sniper","\r\nskel_sniper.png\r\nsize: 256,128\r\nformat: RGBA8888\r\nfilter: Linear,Linear\r\nrepeat: none\r\nicon_jj_cheng\r\n  rotate: false\r\n  xy: 136, 71\r\n  size: 44, 30\r\n  orig: 68, 68\r\n  offset: 12, 19\r\n  index: -1\r\nicon_jj_hong\r\n  rotate: false\r\n  xy: 136, 39\r\n  size: 44, 30\r\n  orig: 68, 68\r\n  offset: 12, 19\r\n  index: -1\r\nicon_jj_huang\r\n  rotate: false\r\n  xy: 182, 71\r\n  size: 44, 30\r\n  orig: 68, 68\r\n  offset: 12, 19\r\n  index: -1\r\nicon_jj_lan\r\n  rotate: false\r\n  xy: 182, 39\r\n  size: 44, 30\r\n  orig: 68, 68\r\n  offset: 12, 19\r\n  index: -1\r\nicon_jj_lv\r\n  rotate: false\r\n  xy: 72, 7\r\n  size: 44, 30\r\n  orig: 68, 68\r\n  offset: 12, 19\r\n  index: -1\r\nicon_jj_qing\r\n  rotate: false\r\n  xy: 118, 7\r\n  size: 44, 30\r\n  orig: 68, 68\r\n  offset: 12, 19\r\n  index: -1\r\nicon_jj_zi\r\n  rotate: false\r\n  xy: 164, 7\r\n  size: 43, 30\r\n  orig: 68, 68\r\n  offset: 13, 19\r\n  index: -1\r\njuji_shang\r\n  rotate: false\r\n  xy: 2, 33\r\n  size: 68, 68\r\n  orig: 68, 68\r\n  offset: 0, 0\r\n  index: -1\r\njuji_xia\r\n  rotate: false\r\n  xy: 72, 39\r\n  size: 62, 62\r\n  orig: 62, 62\r\n  offset: 0, 0\r\n  index: -1\r\njuji_yanpi\r\n  rotate: false\r\n  xy: 2, 2\r\n  size: 60, 29\r\n  orig: 60, 29\r\n  offset: 0, 0\r\n  index: -1\r\n",["skel_sniper.png"],{"skeleton":{"hash":"UmYoYtUKDPRCrx/n6hXtJbbsNbI","spine":"3.8.99","x":-58.1,"y":-269.25,"width":109.6,"height":311,"images":"./images/","audio":"D:/新哥/泡泡龙/狙击"},"bones":[{"name":"root"},{"name":"juji_shang","parent":"root","color":"ff0000ff"},{"name":"juji_yanpi","parent":"juji_shang","x":-1.34,"y":48.58,"color":"36ff05ff"},{"name":"icon_jj_cheng","parent":"juji_shang","y":1.13,"color":"ffd700ff"},{"name":"juji_yanpi2","parent":"juji_shang","x":-1.34,"y":-41.54,"scaleY":-1,"color":"36ff05ff"}],"slots":[{"name":"juji_xia","bone":"juji_shang","attachment":"juji_xia"},{"name":"icon_jj_cheng","bone":"icon_jj_cheng","attachment":"icon_jj_yan"},{"name":"juji_yanpi","bone":"juji_yanpi","attachment":"juji_yanpi"},{"name":"juji_yanpi2","bone":"juji_yanpi2","attachment":"juji_yanpi"},{"name":"juji_shang","bone":"juji_shang","attachment":"juji_shang"}],"skins":[{"name":"default","attachments":{"juji_shang":{"juji_shang":{"width":68,"height":68}},"juji_xia":{"juji_xia":{"x":-0.49,"y":-0.47,"width":62,"height":62}},"juji_yanpi":{"juji_yanpi":{"type":"mesh","hull":8,"width":60,"height":29,"uvs":[1,0.44985,1,0.80144,1,1,0,1,0,0.78806,0,0.45823,0.25964,0,0.80234,0],"triangles":[4,5,6,7,0,1,3,4,6,6,7,1,2,6,1,3,6,2],"vertices":[31.1,-5.27,31.1,-15.46,31.1,-21.22,-28.9,-21.22,-28.9,-15.07,-28.9,-5.51,-13.32,7.78,19.24,7.78],"edges":[4,6,10,12,12,14,14,0,6,8,8,10,0,2,2,4]}},"juji_yanpi2":{"juji_yanpi":{"type":"mesh","hull":6,"width":60,"height":29,"uvs":[1,0.44985,1,1,0,1,0,0.45823,0.25964,0,0.80234,0],"triangles":[2,3,4,5,0,1,4,5,1,2,4,1],"vertices":[31.1,-5.27,31.1,-21.22,-28.9,-21.22,-28.9,-5.51,-13.32,7.78,19.24,7.78],"edges":[2,4,4,6,6,8,8,10,2,0,10,0]}}}},{"name":"cheng","attachments":{"icon_jj_cheng":{"icon_jj_yan":{"name":"icon_jj_cheng","y":-1.13,"width":68,"height":68}}}},{"name":"hong","attachments":{"icon_jj_cheng":{"icon_jj_yan":{"name":"icon_jj_hong","y":-1.13,"width":68,"height":68}}}},{"name":"huang","attachments":{"icon_jj_cheng":{"icon_jj_yan":{"name":"icon_jj_huang","y":-1.13,"width":68,"height":68}}}},{"name":"lan","attachments":{"icon_jj_cheng":{"icon_jj_yan":{"name":"icon_jj_lan","y":-1.13,"width":68,"height":68}}}},{"name":"lv","attachments":{"icon_jj_cheng":{"icon_jj_yan":{"name":"icon_jj_lv","y":-1.13,"width":68,"height":68}}}},{"name":"qing","attachments":{"icon_jj_cheng":{"icon_jj_yan":{"name":"icon_jj_qing","y":-1.13,"width":68,"height":68}}}},{"name":"zi","attachments":{"icon_jj_cheng":{"icon_jj_yan":{"name":"icon_jj_zi","y":-1.13,"width":68,"height":68}}}}],"animations":{"play":{"bones":{"root":{"translate":[{"curve":"stepped"},{"time":1.6667}]},"juji_yanpi":{"translate":[{"y":-6.72,"curve":"stepped"},{"time":2.7,"y":-6.72},{"time":2.7333,"y":-29.49},{"time":2.8,"y":-45.44,"curve":"stepped"},{"time":2.8667,"y":-45.44},{"time":2.9,"y":-29.49},{"time":2.9667,"y":-6.72,"curve":"stepped"},{"time":3.3333,"y":-6.72}]},"juji_yanpi2":{"translate":[{"y":-1.55,"curve":"stepped"},{"time":3.3333,"y":-1.55}]},"icon_jj_cheng":{"translate":[{},{"time":1.6667,"y":-2.42},{"time":3.3333}]}},"deform":{"default":{"juji_yanpi":{"juji_yanpi":[{"curve":"stepped","vertices":[-9.70199,-14.35699,-9.46199,-5.644,-9.70199,-1.47,10.48597,0,10.12599,-4.648,10.48597,-12.88699,1.76401,-21.02102,-1.176,-21.31501]},{"time":2.7,"vertices":[-9.70199,-14.35699,-9.46199,-5.644,-9.70199,-1.47,10.48597,0,10.12599,-4.648,10.48597,-12.88699,1.76401,-21.02102,-1.176,-21.31501]},{"time":2.7333,"vertices":[-3.52799,-1.47,0,0,0,0,0,0,0,0,2.94,-0.88199,2.64599,-3.23399,-5.292,-3.528]},{"time":2.8,"curve":"stepped","vertices":[1.32001,13.074,0,0,-2.121,0.606,4.54501,-1.21201,0,0,-2.72097,10.05201,-8.412,6.205,-5.292,11.92499]},{"time":2.8667,"vertices":[1.32001,13.074,0,0,-2.121,0.606,4.54501,-1.21201,0,0,-2.72097,10.05201,-8.412,6.205,-5.292,11.92499]},{"time":2.9,"vertices":[-3.52799,-1.47,0,0,0,0,0,0,0,0,2.94,-0.88199,2.64599,-3.23399,-5.292,-3.528]},{"time":2.9667,"curve":"stepped","vertices":[-9.70199,-14.35699,-9.46199,-5.644,-9.70199,-1.47,10.48597,0,10.12599,-4.648,10.48597,-12.88699,1.76401,-21.02102,-1.176,-21.31501]},{"time":3.3333,"vertices":[-9.70199,-14.35699,-9.46199,-5.644,-9.70199,-1.47,10.48597,0,10.12599,-4.648,10.48597,-12.88699,1.76401,-21.02102,-1.176,-21.31501]}]},"juji_yanpi2":{"juji_yanpi":[{"curve":"stepped","vertices":[-9.70199,-14.35699,-9.70199,-1.47,10.48597,0,10.48597,-12.88699,1.76401,-21.02102,-1.176,-21.31501]},{"time":3.3333,"vertices":[-9.70199,-14.35699,-9.70199,-1.47,10.48597,0,10.48597,-12.88699,1.76401,-21.02102,-1.176,-21.31501]}]}}}}}},[0]]],0,0,[0],[-1],[0]]
