{"type":"View","props":{"y":0,"x":0,"width":1136,"top":0,"right":0,"presetID":1,"name":"HzzsdkSameGame","left":0,"isPresetRoot":true,"height":640,"bottom":0},"compId":235,"child":[{"type":"Image","props":{"top":0,"skin":"General/main_pic_bg.jpg","right":0,"presetID":17,"name":"bg","left":0,"bottom":0},"compId":252},{"type":"Button","props":{"top":0,"stateNum":1,"skin":"General/play_btn_back.png","presetID":4,"name":"btnClose","left":0},"compId":238},{"type":"List","props":{"repeatY":1,"repeatX":1,"renderType":"render","presetID":18,"name":"list_Banner","hScrollBarSkin":"General/hscroll.png","centerY":0,"centerX":0,"y":-140.5,"x":-185,"width":766,"stateNum":1,"skin":"Rank/rank_pic_rewardsbg.png","sizeGrid":"36,28,38,18","height":359},"compId":309,"child":[{"type":"Box","props":{"y":0,"x":0,"renderType":"render","presetID":18,"width":766,"stateNum":1,"skin":"Rank/rank_pic_rewardsbg.png","sizeGrid":"36,28,38,18","name":"MaxBanner","height":359,"centerY":0,"centerX":0},"compId":308,"child":[{"type":"Button","props":{"y":-140.5,"x":-185,"width":766,"stateNum":1,"skin":"Rank/rank_pic_rewardsbg.png","sizeGrid":"36,28,38,18","presetID":18,"name":"MaxBanner","height":359,"centerY":0,"centerX":0},"compId":285},{"type":"Label","props":{"y":90.5,"x":172.5,"width":421,"text":"0","presetID":20,"name":"text","height":178,"fontSize":50,"font":"SimHei"},"compId":312}]}]},{"type":"Tab","props":{"width":233,"stateNum":2,"space":10,"skin":"Rank/rank10.png","presetID":19,"name":"tab_List","labels":",,","height":40,"centerY":253,"centerX":0},"compId":310}],"loadList":["General/main_pic_bg.jpg","General/play_btn_back.png","General/hscroll.png","Rank/rank_pic_rewardsbg.png","Rank/rank10.png"],"loadList3D":[]}