{"width":256,"imagePath":"w2_ani_tex.png","height":128,"name":"w2_ani","SubTexture":[{"y":1,"frameX":0,"frameY":0,"width":103,"frameWidth":104,"height":124,"name":"w2_shadow","frameHeight":124,"x":1},{"width":22,"y":81,"height":36,"name":"w2_leg1","x":106},{"y":103,"frameX":0,"frameY":0,"width":14,"frameWidth":14,"height":11,"name":"w2_mouth","frameHeight":12,"x":130},{"y":81,"frameX":0,"frameY":0,"width":35,"frameWidth":36,"height":20,"name":"w2_head","frameHeight":20,"x":130},{"width":78,"y":1,"height":78,"name":"w2_body","x":106}]}