[{"__type__":"cc.LabelAtlas","_name":"yx_11","spriteFrame":{"__uuid__":"d9KQsG4D1GH6K/iDCNfUVw"},"fontSize":93.28,"_fntConfig":{"commonHeight":106,"fontSize":93,"atlasName":"yx_11","fontDefDictionary":{"48":{"rect":{"x":0,"y":0,"width":80,"height":106},"xOffset":0,"yOffset":0,"xAdvance":80},"49":{"rect":{"x":80,"y":0,"width":80,"height":106},"xOffset":0,"yOffset":0,"xAdvance":80},"50":{"rect":{"x":160,"y":0,"width":80,"height":106},"xOffset":0,"yOffset":0,"xAdvance":80},"51":{"rect":{"x":240,"y":0,"width":80,"height":106},"xOffset":0,"yOffset":0,"xAdvance":80},"52":{"rect":{"x":320,"y":0,"width":80,"height":106},"xOffset":0,"yOffset":0,"xAdvance":80},"53":{"rect":{"x":400,"y":0,"width":80,"height":106},"xOffset":0,"yOffset":0,"xAdvance":80},"54":{"rect":{"x":480,"y":0,"width":80,"height":106},"xOffset":0,"yOffset":0,"xAdvance":80},"55":{"rect":{"x":560,"y":0,"width":80,"height":106},"xOffset":0,"yOffset":0,"xAdvance":80},"56":{"rect":{"x":640,"y":0,"width":80,"height":106},"xOffset":0,"yOffset":0,"xAdvance":80},"57":{"rect":{"x":720,"y":0,"width":80,"height":106},"xOffset":0,"yOffset":0,"xAdvance":80}},"kerningDict":{}}},{"__type__":"cc.SpriteFrame","content":{"name":"yx_11","texture":"few8jaV2JKyJkqICR2H4eF","rect":[0,0,800,105],"offset":[0,0.5],"originalSize":[800,106],"capInsets":[0,0,0,0]}}]