{"frameRate":24,"name":"s1_2ani","version":"5.5","compatibleVersion":"5.5","armature":[{"type":"Armature","frameRate":24,"name":"Armature","aabb":{"x":-101,"y":-95,"width":202,"height":190},"bone":[{"name":"root"},{"name":"bone","parent":"root"},{"name":"s1_4_1","parent":"bone"},{"name":"s1_3_1","parent":"bone","transform":{"x":50,"y":-15}},{"name":"s1_3_11","parent":"bone","transform":{"x":-50,"y":-15,"scX":-1}},{"name":"s1_2_1","parent":"s1_3_1","transform":{"x":2,"y":-9}},{"name":"s1_2_11","parent":"s1_3_11","transform":{"y":-9,"scX":-1}},{"name":"s1_1_1","parent":"s1_3_1","transform":{"x":10,"y":-12}},{"name":"s1_1_11","parent":"s1_3_11","transform":{"x":10,"y":-12}}],"slot":[{"name":"s1_4_1","parent":"s1_4_1"},{"name":"s1_3_1","parent":"s1_3_1"},{"name":"s1_3_11","parent":"s1_3_11"},{"name":"s1_2_1","parent":"s1_2_1"},{"name":"s1_2_11","parent":"s1_2_11"},{"name":"s1_1_1","parent":"s1_1_1"},{"name":"s1_1_11","parent":"s1_1_11"}],"skin":[{"slot":[{"name":"s1_1_11","display":[{"name":"s1_1_2"}]},{"name":"s1_1_1","display":[{"name":"s1_1_2"}]},{"name":"s1_4_1","display":[{"name":"s1_4_2"}]},{"name":"s1_3_1","display":[{"name":"s1_3_2","transform":{"y":20}}]},{"name":"s1_2_1","display":[{"name":"s1_2_2"}]},{"name":"s1_3_11","display":[{"name":"s1_3_2","transform":{"y":20}}]},{"name":"s1_2_11","display":[{"name":"s1_2_2"}]}]}],"animation":[{"duration":4,"playTimes":0,"name":"idle","bone":[{"name":"s1_4_1","translateFrame":[{"duration":2,"tweenEasing":0},{"duration":2,"tweenEasing":0,"y":-3},{"duration":0}]},{"name":"s1_3_1","translateFrame":[{"duration":2,"tweenEasing":0},{"duration":2,"tweenEasing":0,"x":3},{"duration":0}]},{"name":"s1_3_11","translateFrame":[{"duration":2,"tweenEasing":0},{"duration":2,"tweenEasing":0,"x":-3},{"duration":0}]},{"name":"s1_2_11","rotateFrame":[{"duration":2,"tweenEasing":0},{"duration":2,"tweenEasing":0,"rotate":180},{"duration":0}]},{"name":"s1_2_1","rotateFrame":[{"duration":2,"tweenEasing":0},{"duration":2,"tweenEasing":0,"rotate":180},{"duration":0}]}]}],"defaultActions":[{"gotoAndPlay":"idle"}]}]}